asana_preview/__init__.py
asana_preview/api_client.py
asana_preview/configuration.py
asana_preview/rest.py
asana_preview/api/__init__.py
asana_preview/api/attachments_api.py
asana_preview/api/audit_log_api_api.py
asana_preview/api/batch_api_api.py
asana_preview/api/custom_field_settings_api.py
asana_preview/api/custom_fields_api.py
asana_preview/api/events_api.py
asana_preview/api/goal_relationships_api.py
asana_preview/api/goals_api.py
asana_preview/api/jobs_api.py
asana_preview/api/memberships_api.py
asana_preview/api/organization_exports_api.py
asana_preview/api/portfolio_memberships_api.py
asana_preview/api/portfolios_api.py
asana_preview/api/project_briefs_api.py
asana_preview/api/project_memberships_api.py
asana_preview/api/project_statuses_api.py
asana_preview/api/project_templates_api.py
asana_preview/api/projects_api.py
asana_preview/api/rules_api.py
asana_preview/api/sections_api.py
asana_preview/api/status_updates_api.py
asana_preview/api/stories_api.py
asana_preview/api/tags_api.py
asana_preview/api/task_templates_api.py
asana_preview/api/tasks_api.py
asana_preview/api/team_memberships_api.py
asana_preview/api/teams_api.py
asana_preview/api/time_periods_api.py
asana_preview/api/time_tracking_entries_api.py
asana_preview/api/typeahead_api.py
asana_preview/api/user_task_lists_api.py
asana_preview/api/users_api.py
asana_preview/api/webhooks_api.py
asana_preview/api/workspace_memberships_api.py
asana_preview/api/workspaces_api.py
asana_preview/pagination/__init__.py
asana_preview/pagination/event_iterator.py
asana_preview/pagination/page_iterator.py
test/__init__.py
test/test_attachments_api.py
test/test_audit_log_api_api.py
test/test_batch_api_api.py
test/test_custom_field_settings_api.py
test/test_custom_fields_api.py
test/test_events_api.py
test/test_goal_relationships_api.py
test/test_goals_api.py
test/test_jobs_api.py
test/test_memberships_api.py
test/test_organization_exports_api.py
test/test_portfolio_memberships_api.py
test/test_portfolios_api.py
asana_preview-1.0.39.dist-info/METADATA
asana_preview-1.0.39.dist-info/WHEEL
asana_preview-1.0.39.dist-info/top_level.txt
asana_preview-1.0.39.dist-info/RECORD
