Metadata-Version: 2.1
Name: asana-preview
Version: 1.0.39
Summary: Asana
Home-page: http://github.com/asana/python-asana-preview
Author: Asana, Inc
License: MIT
Keywords: asana,Asana
Requires-Dist: certifi >=2017.4.17
Requires-Dist: python-dateutil >=2.1
Requires-Dist: six >=1.10
Requires-Dist: urllib3 >=1.23
